plover_treal.py
plover_treal-1.0.1.dist-info/DESCRIPTION.rst
plover_treal-1.0.1.dist-info/METADATA
plover_treal-1.0.1.dist-info/RECORD
plover_treal-1.0.1.dist-info/WHEEL
plover_treal-1.0.1.dist-info/entry_points.txt
plover_treal-1.0.1.dist-info/metadata.json
plover_treal-1.0.1.dist-info/top_level.txt
plover_treal-1.0.1.dist-info/zip-safe
